{
  "character_id": "66d89a85-3323-444c-907d-67f7d130c6e6",
  "id": "b0c20061-e601-41e6-b2b6-1500da9e3415",
  "name": "Finito",
  "trainer_id": "5397e243-6cac-484f-9722-2d0697326269",
  "trainer_name": "uniqueusern",
  "matches": {
    "2022-11-18T04:38:06.367781+00:00": {
      "this_amiibo": {
        "rating": -0.43542447124568895,
        "rating_mu": 17.9084546087436,
        "rating_sigma": 6.1146263599964294,
        "result": "loss"
      },
      "opponent": {
        "character_id": "fe995f08-d261-47ba-ac69-81bbd272f8ce",
        "id": "e607ee9e-a715-495d-8d13-3fed2ac29bd7",
        "name": "Banjonetta",
        "rating": 16.270342191398846,
        "trainer_id": "00f2b5fe-c43c-45ec-a979-430486c2ee21",
        "trainer_name": "sheepguy1234",
        "result": "win"
      }
    },
    "2022-12-17T23:22:29.847172+00:00": {
      "this_amiibo": {
        "rating": -0.12285022842081261,
        "rating_mu": 15.593571359039082,
        "rating_sigma": 5.238807195819965,
        "result": "loss"
      },
      "opponent": {
        "character_id": "e2531ffe-e834-49ae-b233-56386472a6ed",
        "id": "2ae42222-bd3b-4e13-b166-70d81811ece5",
        "name": "SpaceMommy",
        "rating": 17.98046257742565,
        "trainer_id": "6927c775-f0ca-4ba7-840c-cb53ff1520c6",
        "trainer_name": "froyoxeno",
        "result": "win"
      }
    },
    "2022-12-30T19:38:56.741717+00:00": {
      "this_amiibo": {
        "rating": 5.126858016886516,
        "rating_mu": 18.448946687507853,
        "rating_sigma": 4.440696223540446,
        "result": "win"
      },
      "opponent": {
        "character_id": "d65e8fc2-a593-4fef-bead-408a967fbb1e",
        "id": "203e78c5-7c82-4129-a80d-2de7a14705ff",
        "name": "Anakin",
        "rating": 13.232787467014212,
        "trainer_id": "6bf29b87-d415-4be4-a384-198d70a63eaf",
        "trainer_name": "WynnThornton",
        "result": "loss"
      }
    },
    "2023-01-03T16:20:18.371576+00:00": {
      "this_amiibo": {
        "rating": 8.528295594034452,
        "rating_mu": 20.536298912068954,
        "rating_sigma": 4.002667772678167,
        "result": "win"
      },
      "opponent": {
        "character_id": "facf1100-a53c-4f9c-bdf3-8612b0df2330",
        "id": "d7c190a8-6080-4534-bf14-15a0d85d95d1",
        "name": "jamickel",
        "rating": 7.0756714093966355,
        "trainer_id": "6b27ede3-0015-42da-83e9-14148f408041",
        "trainer_name": "jothehutt",
        "result": "loss"
      }
    },
    "2023-01-07T09:39:30.378227+00:00": {
      "this_amiibo": {
        "rating": 12.210085960745255,
        "rating_mu": 22.845591136707263,
        "rating_sigma": 3.545168391987336,
        "result": "win"
      },
      "opponent": {
        "character_id": "7c869bdb-0101-4aa7-9ea8-82f1d7420928",
        "id": "a81546ce-6adf-4157-82af-bc91cd1c2c11",
        "name": "Somnius",
        "rating": 18.855275951643677,
        "trainer_id": "c72590ae-93c9-4132-99b2-b8f957919ed3",
        "trainer_name": "Leonard_Lauryn",
        "result": "loss"
      }
    },
    "2023-01-16T03:30:01.641685+00:00": {
      "this_amiibo": {
        "rating": 11.745539101356496,
        "rating_mu": 21.489573265269417,
        "rating_sigma": 3.248011387970974,
        "result": "loss"
      },
      "opponent": {
        "character_id": "3e8519a2-faa6-4bcc-98b9-bff3ac95b504",
        "id": "03c0ad42-e86e-4b54-89d6-b8110537f7ed",
        "name": "Meta",
        "rating": 20.396167411901995,
        "trainer_id": "eb1a1462-8797-4683-9357-0c3ba91b599a",
        "trainer_name": "Gamer_gaben1",
        "result": "win"
      }
    },
    "2023-01-18T15:00:03.990577+00:00": {
      "this_amiibo": {
        "rating": 13.10672912561495,
        "rating_mu": 22.280201969083432,
        "rating_sigma": 3.057824281156161,
        "result": "win"
      },
      "opponent": {
        "character_id": "4d6019ea-9540-4dfe-a6d9-56caa35e7047",
        "id": "eac62453-ebfc-4e40-a486-9cdea665e132",
        "name": "Colby",
        "rating": 13.149739584268769,
        "trainer_id": "479b93ff-1d93-4e65-88c9-8cbfff7e08fc",
        "trainer_name": "SquallDBC",
        "result": "loss"
      }
    },
    "2023-01-22T09:08:55.653878+00:00": {
      "this_amiibo": {
        "rating": 12.155624938663081,
        "rating_mu": 20.615770584877843,
        "rating_sigma": 2.820048548738254,
        "result": "loss"
      },
      "opponent": {
        "character_id": "4d6019ea-9540-4dfe-a6d9-56caa35e7047",
        "id": "eac62453-ebfc-4e40-a486-9cdea665e132",
        "name": "Colby",
        "rating": 14.001498019867665,
        "trainer_id": "479b93ff-1d93-4e65-88c9-8cbfff7e08fc",
        "trainer_name": "SquallDBC",
        "result": "win"
      }
    },
    "2023-01-25T15:48:25.582012+00:00": {
      "this_amiibo": {
        "rating": 13.023269967333619,
        "rating_mu": 21.239482589477277,
        "rating_sigma": 2.7387375407145527,
        "result": "win"
      },
      "opponent": {
        "character_id": "8bae1c7b-a783-45ee-a246-1ab9507080ba",
        "id": "14086312-6be5-4ae9-9b36-740c59222364",
        "name": "Mr Fist",
        "rating": 0.07935807747742629,
        "trainer_id": "78c43ad8-a6ad-4132-a9ff-7e156da1901e",
        "trainer_name": "rurpking22",
        "result": "loss"
      }
    },
    "2023-01-27T19:21:34.124068+00:00": {
      "this_amiibo": {
        "rating": 13.23842426026603,
        "rating_mu": 20.630787293012148,
        "rating_sigma": 2.4641210109153726,
        "result": "win"
      },
      "opponent": {
        "character_id": "bcfaf3a7-049c-478f-901f-31ac873260f3",
        "id": "5f8868dc-42ef-49d0-bf57-99558b88f68a",
        "name": "Spaghetti",
        "rating": 12.116399395932973,
        "trainer_id": "572ea3a2-7f62-4814-9089-dd5e78bb246f",
        "trainer_name": "Strange_Fate",
        "result": "loss"
      }
    },
    "2023-01-27T16:36:48.681852+00:00": {
      "this_amiibo": {
        "rating": 12.340407346700363,
        "rating_mu": 20.0512503932455,
        "rating_sigma": 2.5702810155150457,
        "result": "loss"
      },
      "opponent": {
        "character_id": "4d6019ea-9540-4dfe-a6d9-56caa35e7047",
        "id": "eac62453-ebfc-4e40-a486-9cdea665e132",
        "name": "Colby",
        "rating": 14.61400070303982,
        "trainer_id": "479b93ff-1d93-4e65-88c9-8cbfff7e08fc",
        "trainer_name": "SquallDBC",
        "result": "win"
      }
    },
    "2023-02-08T12:53:02.363578+00:00": {
      "this_amiibo": {
        "rating": 13.890316745464101,
        "rating_mu": 21.057425486795136,
        "rating_sigma": 2.389036247110345,
        "result": "win"
      },
      "opponent": {
        "character_id": "d444e8eb-0140-4e51-9203-b374d9a4431d",
        "id": "416eea16-cadc-446e-a054-d6b4791803c1",
        "name": "SSD Chomp",
        "rating": 7.328185558735697,
        "trainer_id": "52f01d9e-90d0-44d3-9846-d969ad5f091f",
        "trainer_name": "spike2the9th",
        "result": "loss"
      }
    },
    "2023-02-17T11:56:39.607588+00:00": {
      "this_amiibo": {
        "rating": 13.355431475199262,
        "rating_mu": 20.174884517043516,
        "rating_sigma": 2.2731510139480844,
        "result": "loss"
      },
      "opponent": {
        "character_id": "5c63c8cc-6afa-4bd5-ad30-815856cb845d",
        "id": "911ccc15-c6ed-43d6-853d-1e148a458582",
        "name": "Cereza",
        "rating": 16.194718830383714,
        "trainer_id": "72dbf100-42cd-432c-993b-ac2d26cfcaa6",
        "trainer_name": "Persesco",
        "result": "win"
      }
    },
    "2023-02-20T06:31:42.154532+00:00": {
      "this_amiibo": {
        "rating": 12.842507197112845,
        "rating_mu": 19.415203008246888,
        "rating_sigma": 2.1908986037113474,
        "result": "loss"
      },
      "opponent": {
        "character_id": "eea3bb5b-564a-46c4-9c4c-8cef6e59c8b1",
        "id": "5d338d1c-d958-4f82-bdbb-db7692d67370",
        "name": "billy□",
        "rating": 10.045918820578171,
        "trainer_id": "b10876b5-7251-465f-9881-c964cde57340",
        "trainer_name": "nozomup",
        "result": "win"
      }
    },
    "2023-02-27T20:27:36.653940+00:00": {
      "this_amiibo": {
        "rating": 13.761696724537769,
        "rating_mu": 20.08002573428181,
        "rating_sigma": 2.1061096699146806,
        "result": "win"
      },
      "opponent": {
        "character_id": "4c8513b8-a7c7-42f4-a4d4-55f5415d92fb",
        "id": "823d6e96-5cab-4133-bcc7-7f398cd51fd9",
        "name": "Michele",
        "rating": 15.937651690274745,
        "trainer_id": "fff1df31-fc68-4fba-8d11-7e4016df1268",
        "trainer_name": "patspatchgaming_yt",
        "result": "loss"
      }
    },
    "2023-02-28T13:09:43.976073+00:00": {
      "this_amiibo": {
        "rating": 14.316969387773709,
        "rating_mu": 20.455136680240035,
        "rating_sigma": 2.046055764155442,
        "result": "win"
      },
      "opponent": {
        "character_id": "cc43dc32-d6fd-43eb-be16-47c498521272",
        "id": "755be348-8c86-4afa-8e79-4921876c6e0c",
        "name": "FaxMachine",
        "rating": 13.379914485255716,
        "trainer_id": "2f9c8c00-fa6a-404d-8718-68edf85cb21f",
        "trainer_name": "irongelatin",
        "result": "loss"
      }
    },
    "2023-03-01T01:09:30.960673+00:00": {
      "this_amiibo": {
        "rating": 14.802874506502658,
        "rating_mu": 20.782549376672836,
        "rating_sigma": 1.9932249567233926,
        "result": "win"
      },
      "opponent": {
        "character_id": "cc43dc32-d6fd-43eb-be16-47c498521272",
        "id": "755be348-8c86-4afa-8e79-4921876c6e0c",
        "name": "FaxMachine",
        "rating": 13.286536020321842,
        "trainer_id": "2f9c8c00-fa6a-404d-8718-68edf85cb21f",
        "trainer_name": "irongelatin",
        "result": "loss"
      }
    },
    "2023-03-05T22:58:02.040952+00:00": {
      "this_amiibo": {
        "rating": 15.524751731467607,
        "rating_mu": 21.31153112927946,
        "rating_sigma": 1.928926465937284,
        "result": "win"
      },
      "opponent": {
        "character_id": "7f5de07d-9c82-45fb-adae-73c8a2b811e3",
        "id": "0f3e946b-9b48-4049-8e59-41465ce26699",
        "name": "PaulRevere",
        "rating": 18.027736673669907,
        "trainer_id": "d0e3f535-e180-4251-94b6-6c528f278d1e",
        "trainer_name": "CSharp__",
        "result": "loss"
      }
    }
  }
}