{
  "character_id": "4c8513b8-a7c7-42f4-a4d4-55f5415d92fb",
  "id": "8cc5e1e6-7f35-40b2-88de-6c4a1239c714",
  "name": "Ameya",
  "trainer_id": "a0059ec8-ffe2-402f-a00a-f0b8356afdfe",
  "trainer_name": "raid_boss_09",
  "matches": {
    "2022-05-09T23:02:45.882417+00:00": {
      "this_amiibo": {
        "rating": 13.256821300920791,
        "rating_mu": 31.95096729095696,
        "rating_sigma": 6.231381996678723,
        "result": "win"
      },
      "opponent": {
        "character_id": "4dcbb633-58b0-481a-9d6a-c350b2c08640",
        "id": "9a4b27e3-05e2-4f07-9133-db545f492fe6",
        "name": "Drip",
        "rating": 19.99195331072926,
        "trainer_id": "80f98683-a318-47dd-bcf2-93f67d0878d4",
        "trainer_name": "Sir_Dragonite",
        "result": "loss"
      }
    },
    "2023-05-13T21:50:41.345375+00:00": {
      "this_amiibo": {
        "rating": 21.749386106783497,
        "rating_mu": 36.598769137660454,
        "rating_sigma": 4.949794343625652,
        "result": "win"
      },
      "opponent": {
        "character_id": "9e7024ec-4a72-4887-bdad-4adbb9b0e3a9",
        "id": "7367a48d-cab3-435b-a932-34c216ca08a4",
        "name": "BoogerKong",
        "rating": 32.44837823596097,
        "trainer_id": "a492c8da-e8ac-4a2b-a5d0-e9d14c2b1642",
        "trainer_name": "DragonFroot_",
        "result": "loss"
      }
    },
    "2023-05-15T08:41:09.266975+00:00": {
      "this_amiibo": {
        "rating": 21.71694382443039,
        "rating_mu": 34.85399350546468,
        "rating_sigma": 4.379016560344763,
        "result": "loss"
      },
      "opponent": {
        "character_id": "2cf4a409-b186-43a9-948f-175abbef3426",
        "id": "88e180cf-8176-4cb7-bca5-51470044cb79",
        "name": "Kukui Cat★",
        "rating": 36.663465601959004,
        "trainer_id": "a28a2913-c930-4acd-9cb7-d8a53b228189",
        "trainer_name": "River_Tethys",
        "result": "win"
      }
    },
    "2023-07-02T03:45:58.740970+00:00": {
      "this_amiibo": {
        "rating": 26.702538887064296,
        "rating_mu": 37.98964531340993,
        "rating_sigma": 3.762368808781878,
        "result": "win"
      },
      "opponent": {
        "character_id": "6a728c16-df81-4513-9896-3222fbce4ea1",
        "id": "ef8eceea-2c2e-4c7c-bbf8-06cc39fcffbf",
        "name": "Sniper",
        "rating": 36.63641033554815,
        "trainer_id": "f346091f-8917-49bc-b479-b0c568026dbf",
        "trainer_name": "RazorForce21",
        "result": "loss"
      }
    },
    "2023-07-02T17:06:48.392855+00:00": {
      "this_amiibo": {
        "rating": 26.107344542346432,
        "rating_mu": 36.37428726100052,
        "rating_sigma": 3.4223142395513615,
        "result": "loss"
      },
      "opponent": {
        "character_id": "1aedb3f5-e352-4ebf-b701-7502bbf62366",
        "id": "11fd9f89-7249-403b-bae7-e82435b06e87",
        "name": "Mickey",
        "rating": 32.15482196834789,
        "trainer_id": "3356a8c1-d363-4d61-bcae-046cffd1b341",
        "trainer_name": "fammydamammy",
        "result": "win"
      }
    },
    "2023-07-07T19:20:58.940942+00:00": {
      "this_amiibo": {
        "rating": 25.49086128905916,
        "rating_mu": 34.396701694892236,
        "rating_sigma": 2.9686134686110255,
        "result": "loss"
      },
      "opponent": {
        "character_id": "da0c84d7-9c43-4e74-92e7-113194694b25",
        "id": "13511eda-deef-4d5c-81a9-719300d4dee6",
        "name": "Hero",
        "rating": 34.35999577312245,
        "trainer_id": "b10876b5-7251-465f-9881-c964cde57340",
        "trainer_name": "nozomup",
        "result": "win"
      }
    }
  }
}